de_embedding/__init__.py
de_embedding/create_dict.py
de_embedding/load_data.py
de_embedding/data/L1.s2p
de_embedding/data/L2.s2p
de_embedding/data/Line.s2p
de_embedding/data/Mut.s2p
de_embedding/data/RA_dut_RB.s2p
de_embedding/data/Reflect_11.s1p
de_embedding/data/Reflect_22.s1p
de_embedding/data/Thru.s2p
de_embedding/data/dut_only.s2p
de_embedding/data/open.s1p
de_embedding/data/open.s2p
de_embedding/data/simulation_ADS/L1.s2p
de_embedding/data/simulation_ADS/L2.s2p
de_embedding/data/simulation_ADS/RA_dut_RB.s2p
de_embedding/data/simulation_ADS/Thru.s2p
de_embedding/data/simulation_ADS/dut_only.s2p
de_embedding/data/simulation_ADS/open.s2p
de_embedding/modules/__init__.py
de_embedding/modules/methods/__init__.py
de_embedding/modules/methods/calculate_propagation_const.py
de_embedding/modules/methods/calibration_LL.py
de_embedding/modules/methods/calibration_trl.py
de_embedding/modules/methods/calibration_trl_virtual.py
de_embedding/modules/methods/calibration_tvrl.py
de_embedding/modules/methods/modify_phase.py
de_embedding/modules/methods/signal_corrector.py
de_embedding/modules/methods/unwrap_owm.py
de_embedding/modules/postprocessing/__init__.py
de_embedding/modules/postprocessing/aux_post.py
de_embedding/modules/postprocessing/complex_converter.py
de_embedding/modules/postprocessing/post_processing.py
de_embedding/modules/preprocessing/__init__.py
de_embedding/modules/preprocessing/collapse_values.py
de_embedding/modules/preprocessing/preprocessing_sparameters.py
de_embedding/modules/preprocessing/time_domain_gating.py
de_embedding/modules/preprocessing/unwarp_phase.py
de_embedding/modules/visualization/__init__.py
de_embedding/modules/visualization/plot_s_parame.py
de_embedding/modules/visualization/plot_s_parameters.py
de_embedding/modules/windows/__init__.py
de_embedding/modules/windows/window_kaiser.py
de_embedding/modules/windows/window_processor.py
de_embedding_rf-0.3.6.dist-info/METADATA
de_embedding_rf-0.3.6.dist-info/WHEEL
de_embedding_rf-0.3.6.dist-info/top_level.txt
de_embedding_rf-0.3.6.dist-info/RECORD
