Metadata-Version: 2.2
Name: de_embedding_rf
Version: 0.3.6
Summary: methods for de-embedding process: T-R-L, L-L and T-VR-L
Home-page: https://github.com/aplatag/project_de_embedding_rf.git
Author: Aplatag
License: MIT
Requires-Dist: numpy
Requires-Dist: pandas
Requires-Dist: scikit-rf
Requires-Dist: matplotlib
Requires-Dist: scipy
Dynamic: author
Dynamic: description
Dynamic: description-content-type
Dynamic: home-page
Dynamic: license
Dynamic: requires-dist
Dynamic: summary
